Metadata-Version: 1.0
Name: osuex
Version: 0.0.5
Summary: An osu extraction tool for linux users
Home-page: http://packages.python.org/osuex
Author: Jacob Zipper
Author-email: zipper@jacobzipper.com
License: UNKNOWN
Platform: UNKNOWN
